get_data/__init__.py
get_data/polygon_data.py
polygon_guansli-0.1.1.dist-info/METADATA
polygon_guansli-0.1.1.dist-info/WHEEL
polygon_guansli-0.1.1.dist-info/top_level.txt
polygon_guansli-0.1.1.dist-info/RECORD
